autosubmitconfigparser/__init__.py
autosubmitconfigparser/config/__init__.py
autosubmitconfigparser/config/basicconfig.py
autosubmitconfigparser/config/configcommon.py
autosubmitconfigparser/config/yamlparser.py
autosubmitconfigparser/config/files/autosubmit-dummy.yml
autosubmitconfigparser/config/files/autosubmit.yml
autosubmitconfigparser/config/files/expdef-dummy.yml
autosubmitconfigparser/config/files/expdef.yml
autosubmitconfigparser/config/files/git-minimal.yml
autosubmitconfigparser/config/files/jobs-dummy.yml
autosubmitconfigparser/config/files/jobs.yml
autosubmitconfigparser/config/files/local-minimal.yml
autosubmitconfigparser/config/files/platforms-dummy.yml
autosubmitconfigparser/config/files/platforms.yml
log/__init__.py
log/fd_show.py
log/log.py
autosubmitconfigparser-1.0.79.dist-info/METADATA
autosubmitconfigparser-1.0.79.dist-info/WHEEL
autosubmitconfigparser-1.0.79.dist-info/top_level.txt
autosubmitconfigparser-1.0.79.dist-info/RECORD
