Metadata-Version: 2.4
Name: autosubmitconfigparser
Version: 1.0.79
Summary: An utility library that allows to read an Autosubmit 4 experiment configuration.
Home-page: https://earth.bsc.es/gitlab/ces/autosubmit4-config-parser.git
Author: Daniel Beltran Mora
Author-email: daniel.beltran@bsc.es
Keywords: climate,weather,workflow,HPC
Classifier: Programming Language :: Python :: 3.7
Classifier: Programming Language :: Python :: 3.9
Classifier: Programming Language :: Python :: 3.11
Classifier: License :: OSI Approved :: GNU General Public License (GPL)
Classifier: Operating System :: POSIX :: Linux
Requires-Dist: ruamel.yaml==0.18.6
Requires-Dist: mock
Requires-Dist: bscearth.utils
Requires-Dist: configobj
Requires-Dist: pyparsing
Requires-Dist: configparser
Provides-Extra: test
Requires-Dist: pytest; extra == "test"
Requires-Dist: pytest-cov; extra == "test"
Requires-Dist: pytest-mock; extra == "test"
Requires-Dist: ruff; extra == "test"
Provides-Extra: all
Requires-Dist: ruamel.yaml==0.18.6; extra == "all"
Requires-Dist: mock; extra == "all"
Requires-Dist: bscearth.utils; extra == "all"
Requires-Dist: configobj; extra == "all"
Requires-Dist: pyparsing; extra == "all"
Requires-Dist: configparser; extra == "all"
Requires-Dist: pytest; extra == "all"
Requires-Dist: pytest-cov; extra == "all"
Requires-Dist: pytest-mock; extra == "all"
Requires-Dist: ruff; extra == "all"
Dynamic: author
Dynamic: author-email
Dynamic: classifier
Dynamic: description
Dynamic: description-content-type
Dynamic: home-page
Dynamic: keywords
Dynamic: provides-extra
Dynamic: requires-dist
Dynamic: summary
